ipipneo/__init__.py
ipipneo/facet.py
ipipneo/ipipneo.py
ipipneo/model.py
ipipneo/norm.py
ipipneo/quiz.py
ipipneo/reverse.py
ipipneo/utility.py
five_factor_e-1.13.1.dist-info/LICENSE
five_factor_e-1.13.1.dist-info/METADATA
five_factor_e-1.13.1.dist-info/WHEEL
five_factor_e-1.13.1.dist-info/entry_points.txt
five_factor_e-1.13.1.dist-info/top_level.txt
five_factor_e-1.13.1.dist-info/RECORD
