Metadata-Version: 2.1
Name: five-factor-e
Version: 1.13.1
Summary: Big 5 IPIP-NEO Personality Traits
Author: Ederson Corbari, NeuroQuest AI
Author-email: <e@NeuroQuest.ai>
Keywords: IPIP,IPIP-NEO,Big-5,Big-Five,Five-Factor,Personality,Assessment,Psychometrics,Personality-Insights,People-Analytics,Python
Classifier: Environment :: Console
Classifier: License :: OSI Approved :: MIT License
Classifier: Development Status :: 5 - Production/Stable
Classifier: Intended Audience :: Developers
Classifier: Intended Audience :: Science/Research
Classifier: Intended Audience :: Education
Classifier: Programming Language :: Python :: 3
Classifier: Operating System :: OS Independent
Requires-Python: >=3.10
License-File: LICENSE
Provides-Extra: quiz
Requires-Dist: plotext ; extra == 'quiz'
